{
  "manifestVersion": "3.2",
  "admin": {
    "address": "0x86E6c9F509880a9F76E92BBa78384ad42Aa11596",
    "txHash": "0x440019f9e1c3b66589fb6279505f631b01ca3ff1f6686719ea53633e9688c798"
  },
  "proxies": [
    {
      "address": "0x7AbeaE2cE300a1047D3B1662D3510c448fE0C51E",
      "txHash": "0xf90abec50e8126966cfabf0b126dd903c877822318a97210ce57969064f08a48",
      "kind": "transparent"
    }
  ],
  "impls": {
    "0b0f1070672c38cec5a288732f50e0bff094e9b648eefaa31fe915995ed1a7d7": {
      "address": "0x1eE9dD1493d095F755C4298bDBb165CED8A99d29",
      "txHash": "0x225eb3b42738494f2f074ae27296c36d3adcab73944de1c01a71a92d3d924665",
      "layout": {
        "storage": [
          {
            "contract": "Initializable",
            "label": "_initialized",
            "type": "t_bool",
            "src": "../@openzeppelin/contracts-upgradeable/proxy/utils/Initializable.sol:39"
          },
          {
            "contract": "Initializable",
            "label": "_initializing",
            "type": "t_bool",
            "src": "../@openzeppelin/contracts-upgradeable/proxy/utils/Initializable.sol:44"
          },
          {
            "contract": "ContextUpgradeable",
            "label": "__gap",
            "type": "t_array(t_uint256)50_storage",
            "src": "../@openzeppelin/contracts-upgradeable/utils/ContextUpgradeable.sol:31"
          },
          {
            "contract": "ERC20Upgradeable",
            "label": "_balances",
            "type": "t_mapping(t_address,t_uint256)",
            "src": "../@openzeppelin/contracts-upgradeable/token/ERC20/ERC20Upgradeable.sol:37"
          },
          {
            "contract": "ERC20Upgradeable",
            "label": "_allowances",
            "type": "t_mapping(t_address,t_mapping(t_address,t_uint256))",
            "src": "../@openzeppelin/contracts-upgradeable/token/ERC20/ERC20Upgradeable.sol:39"
          },
          {
            "contract": "ERC20Upgradeable",
            "label": "_totalSupply",
            "type": "t_uint256",
            "src": "../@openzeppelin/contracts-upgradeable/token/ERC20/ERC20Upgradeable.sol:41"
          },
          {
            "contract": "ERC20Upgradeable",
            "label": "_name",
            "type": "t_string_storage",
            "src": "../@openzeppelin/contracts-upgradeable/token/ERC20/ERC20Upgradeable.sol:43"
          },
          {
            "contract": "ERC20Upgradeable",
            "label": "_symbol",
            "type": "t_string_storage",
            "src": "../@openzeppelin/contracts-upgradeable/token/ERC20/ERC20Upgradeable.sol:44"
          },
          {
            "contract": "ERC20Upgradeable",
            "label": "__gap",
            "type": "t_array(t_uint256)45_storage",
            "src": "../@openzeppelin/contracts-upgradeable/token/ERC20/ERC20Upgradeable.sol:362"
          },
          {
            "contract": "Token",
            "label": "owner",
            "type": "t_address_payable",
            "src": "Token.sol:8"
          }
        ],
        "types": {
          "t_address_payable": {
            "label": "address payable"
          },
          "t_mapping(t_address,t_uint256)": {
            "label": "mapping(address => uint256)"
          },
          "t_address": {
            "label": "address"
          },
          "t_uint256": {
            "label": "uint256"
          },
          "t_mapping(t_address,t_mapping(t_address,t_uint256))": {
            "label": "mapping(address => mapping(address => uint256))"
          },
          "t_string_storage": {
            "label": "string"
          },
          "t_array(t_uint256)45_storage": {
            "label": "uint256[45]"
          },
          "t_array(t_uint256)50_storage": {
            "label": "uint256[50]"
          },
          "t_bool": {
            "label": "bool"
          }
        }
      }
    },
    "876fdfbb1519b48b2bb8388ed6e3d66e86cc552dfb6a5a57833a74b721aef27a": {
      "address": "0x44A5bdB38f886F80ce034bAf6e7772997728Ca21",
      "txHash": "0xa2f0964cf3bfaf753433e17281b6bf97734a66685f026fd227760df7149a67f5",
      "layout": {
        "storage": [
          {
            "contract": "Initializable",
            "label": "_initialized",
            "type": "t_bool",
            "src": "../@openzeppelin/contracts-upgradeable/proxy/utils/Initializable.sol:39"
          },
          {
            "contract": "Initializable",
            "label": "_initializing",
            "type": "t_bool",
            "src": "../@openzeppelin/contracts-upgradeable/proxy/utils/Initializable.sol:44"
          },
          {
            "contract": "ContextUpgradeable",
            "label": "__gap",
            "type": "t_array(t_uint256)50_storage",
            "src": "../@openzeppelin/contracts-upgradeable/utils/ContextUpgradeable.sol:31"
          },
          {
            "contract": "ERC20Upgradeable",
            "label": "_balances",
            "type": "t_mapping(t_address,t_uint256)",
            "src": "../@openzeppelin/contracts-upgradeable/token/ERC20/ERC20Upgradeable.sol:37"
          },
          {
            "contract": "ERC20Upgradeable",
            "label": "_allowances",
            "type": "t_mapping(t_address,t_mapping(t_address,t_uint256))",
            "src": "../@openzeppelin/contracts-upgradeable/token/ERC20/ERC20Upgradeable.sol:39"
          },
          {
            "contract": "ERC20Upgradeable",
            "label": "_totalSupply",
            "type": "t_uint256",
            "src": "../@openzeppelin/contracts-upgradeable/token/ERC20/ERC20Upgradeable.sol:41"
          },
          {
            "contract": "ERC20Upgradeable",
            "label": "_name",
            "type": "t_string_storage",
            "src": "../@openzeppelin/contracts-upgradeable/token/ERC20/ERC20Upgradeable.sol:43"
          },
          {
            "contract": "ERC20Upgradeable",
            "label": "_symbol",
            "type": "t_string_storage",
            "src": "../@openzeppelin/contracts-upgradeable/token/ERC20/ERC20Upgradeable.sol:44"
          },
          {
            "contract": "ERC20Upgradeable",
            "label": "__gap",
            "type": "t_array(t_uint256)45_storage",
            "src": "../@openzeppelin/contracts-upgradeable/token/ERC20/ERC20Upgradeable.sol:362"
          },
          {
            "contract": "TokenV2",
            "label": "owner",
            "type": "t_address_payable",
            "src": "TokenV2.sol:8"
          }
        ],
        "types": {
          "t_address_payable": {
            "label": "address payable"
          },
          "t_mapping(t_address,t_uint256)": {
            "label": "mapping(address => uint256)"
          },
          "t_address": {
            "label": "address"
          },
          "t_uint256": {
            "label": "uint256"
          },
          "t_mapping(t_address,t_mapping(t_address,t_uint256))": {
            "label": "mapping(address => mapping(address => uint256))"
          },
          "t_string_storage": {
            "label": "string"
          },
          "t_array(t_uint256)45_storage": {
            "label": "uint256[45]"
          },
          "t_array(t_uint256)50_storage": {
            "label": "uint256[50]"
          },
          "t_bool": {
            "label": "bool"
          }
        }
      }
    }
  }
}
